DateTimeEnhanced/DateTimeEnhanced.py
DateTimeEnhanced/__init__.py
datetimeenhanced-0.2.0.dist-info/licenses/LICENSE
datetimeenhanced-0.2.0.dist-info/METADATA
datetimeenhanced-0.2.0.dist-info/WHEEL
datetimeenhanced-0.2.0.dist-info/top_level.txt
datetimeenhanced-0.2.0.dist-info/RECORD
