Metadata-Version: 2.4
Name: DateTimeEnhanced
Version: 0.2.0
License: MIT License
Project-URL: Homepage, https://github.com/twh970723/DateTimeEnhanced
Requires-Python: >=3.11
License-File: LICENSE
Requires-Dist: python-dateutil>=2.8.2
Dynamic: license-file
